[{"title":"20210617-CISCN2021华东南分区赛","url":"/posts/3a78d3e0/"},{"title":"20220311-西湖论剑-IoTSecPartWriteUp","url":"/posts/6451276b/"},{"title":"114新闻部工作手册","url":"/posts/cdf770aa/"},{"title":"hexo搭建博客指北","url":"/posts/9db4668f/"},{"title":"20211127-N^3CTF","url":"/posts/a89e21c0/"},{"title":"20211211-美团CTF","url":"/posts/b83e9e49/"},{"title":"20220108-长安战“疫”","url":"/posts/d42f9c86/"},{"title":"20220409-HZNUCTF","url":"/posts/8de4998e/"},{"title":"CTF密码题是怎么炼成的","url":"/posts/921543e1/"},{"title":"USBKey Learning","url":"/posts/a6b76827/"},{"title":"20210522-NEEPU Sec2021公开赛-CryptoSecWriteUp","url":"/posts/e22cbbee/"},{"title":"20210527-美团CTF-CryptoSecPartWriteUp","url":"/posts/43deb916/"},{"title":"20210516-CISCN2021-CryptoSecPartWriteUp","url":"/posts/766eb6e4/"},{"title":"20210529-DozerCTF-CryptoSecPartWrtieUp","url":"/posts/67700515/"},{"title":"20210626-GKCTF-CryptoSecPartWriteUp","url":"/posts/2d82e8aa/"},{"title":"20200219-VNCTF-CryptoSecWriteUp","url":"/posts/19a278ea/"},{"title":"20210529-春秋杯网络安全联赛春季赛-CryptoSecPartWriteUp","url":"/posts/250213ee/"},{"title":"20210523-宁波市第四届网络安全大赛-CryptoSecWriteUp","url":"/posts/a428a61f/"},{"title":"20210601-NEWSCTF-Nova底登陆WriteUp","url":"/posts/72f0c58/"},{"title":"20210704-TCTF-CryptoSecPartWriteUp","url":"/posts/df43d8e4/"},{"title":"20210710-CTFSHOW CJB-CryptoSecPartWriteUp","url":"/posts/78d3fdb3/"},{"title":"20210731-DAS & 极客巅峰 & UIUCTF2021 & Cryptoctf-CryptoSecPartWriteUp","url":"/posts/fadeeed/"},{"title":"20210807-RAR & BSidesNoida-CryptoSecPartWritUp","url":"/posts/80918a4f/"},{"title":"20210821-corCTF & YauzaCTF-Crypto & OISNTSecPartWriteUp","url":"/posts/493b5ffc/"},{"title":"20210828-WMCTF-CryptoSecPartWriteUp","url":"/posts/37313bc0/"},{"title":"20210908-Untitled-CryptoSecWriteUp","url":"/posts/e245e3dc/"},{"title":"20210911-CSAWCTF-CryptoSecPartWriteUp","url":"/posts/e4da15f1/"},{"title":"20210925-长安杯-CryptoSecPartWriteUp","url":"/posts/1f50d7b8/"},{"title":"20210919-长城杯-CryptoSecWriteUp","url":"/posts/d98f7fed/"},{"title":"20211008-鹤城杯-CryptoSecPartWriteUp","url":"/posts/4ed7c718/"},{"title":"20210929-绿城杯-CryptoSecWriteUp","url":"/posts/85864d0a/"},{"title":"20210903-Blue Whale Freshers & 第六届中国海洋大学信息安全竞赛-CryptoSecPartWriteUp","url":"/posts/ea88a88e/"},{"title":"20211011-莲城杯-CryptoSecWriteUp","url":"/posts/4251790a/"},{"title":"20211030-第四届浙江省大学生网络与信息安全竞赛（决赛）-CryptoSecWriteUp","url":"/posts/2e516684/"},{"title":"20211023-第四届浙江省大学生网络与信息安全竞赛（预赛）-CryptoSecWriteUp","url":"/posts/a2deb6fa/"},{"title":"20211107-陇原战“疫”-CryptoSecWriteUp","url":"/posts/a1174b3b/"},{"title":"20211120-西湖论剑-CryptoSecPartWriteUp","url":"/posts/fbd2fb43/"},{"title":"20211121-湖湘杯-CryptoSecWriteUp","url":"/posts/1ffb9441/"},{"title":"20211113-L3HCTF-CryptoSecPartWriteUp","url":"/posts/90e286aa/"},{"title":"20211206-GWB-CryproSecWriteUp","url":"/posts/8b226326/"},{"title":"20220514-NSSCTF Round#3-CryptoSecWriteUp","url":"/posts/cf0c7406/"},{"title":"20220507-春秋杯网络安全联赛春季赛之勇者山峰-CryptoSecWriteUp","url":"/posts/7195a71e/"},{"title":"20220709-蓝帽杯-CryptoSecWriteUp","url":"/posts/9864757a/"},{"title":"20210814-InCTF & RACTF & SSTF-Crypto & OSINTSecPartWrtieUp","url":"/posts/becd8ce9/"},{"title":"20220826-网鼎杯-CryptoSecWriteUp","url":"/posts/858c0940/"},{"title":"20210821-祥云杯-CryptoSecPartWriteUp","url":"/posts/60aa74b/"},{"title":"20211205-湖湘杯-PwnSecPartWriteUp","url":"/posts/7744a72a/"},{"title":"20220520-CTFSHOW单身杯-CryptoSecWriteUp","url":"/posts/87bed260/"},{"title":"CTFSHOW-funnyrsa & unusualrsa系列","url":"/posts/80806ae5/"},{"title":"20210706-PWNHUB7月公开赛-CryptoSecPartWriteUp","url":"/posts/798f5cbc/"},{"title":"20210920-CTFSHOW月饼杯-CryptoSecWriteUp","url":"/posts/eabdfebd/"},{"title":"20220526-第六届中国海洋大学信息安全竞赛暨Blue Whale CTF-CryptoSecPartWriteUp","url":"/posts/bf1c786b/"},{"title":"20211221-PWHHUB12月赛-CryptoSecWriteUp","url":"/posts/ca24ba5/"},{"title":"20220514-PWNHUB5月赛-CryptoSecWriteUp","url":"/posts/77133399/"},{"title":"20210529-DASCTFxBUUOJ五月大联动-CryptoSecPartWrtieUp","url":"/posts/88b63128/"},{"title":"20210830-DAS8月赛-CryptoSecWriteUp","url":"/posts/67d634b2/"},{"title":"20220522-DAS MAY 出题人挑战赛-CryptoSecWriteUp","url":"/posts/2906a8ab/"},{"title":"20220423-DASxFATE-CryptoSecPartWriteUp","url":"/posts/9171e9d7/"},{"title":"N1BOOK-第七章 CTF之CRYPTO章-N1AES","url":"/posts/dd4bb518/"},{"title":"红明谷2021-ezCRT","url":"/posts/377b2f28/"},{"title":"SUCTF2019-MT","url":"/posts/ca3b3eaf/"},{"title":"20220427-PWNHUB春季赛-CryptoSecWriteUp","url":"/posts/6587a001/"},{"title":"20220802-强网杯-CryptoSecWriteUp","url":"/posts/1986d48b/"},{"title":"20220903-羊城杯-CryptoSecPartWriteUp","url":"/posts/9d8952b1/"}]